lv_ui_testing/__init__.py
lv_ui_testing/_core.py
lv_ui_testing/front_most_vi.py
lv_ui_testing/sub_panel.py
lv_ui_testing/sub_sub_panel.py
lv_ui_testing/ui_testing.py
lv_ui_testing-2.2.0.dist-info/licenses/LICENSE.txt
lv_ui_testing-2.2.0.dist-info/METADATA
lv_ui_testing-2.2.0.dist-info/WHEEL
lv_ui_testing-2.2.0.dist-info/top_level.txt
lv_ui_testing-2.2.0.dist-info/RECORD
