Metadata-Version: 2.4
Name: lv_ui_testing
Version: 2.2.0
Summary: A LabVIEW User Interface Testing framework.
Author-email: Thomas Zilliox <thomas.zilliox67@gmail.com>
License-Expression: MIT
Project-URL: Homepage, https://github.com/ThomasPRZilliox/lv-ui-testing/wiki
Project-URL: Issues, https://github.com/pypa/sampleproject/issues
Classifier: Programming Language :: Python :: 3
Classifier: Operating System :: OS Independent
Requires-Python: >=3.8
License-File: LICENSE.txt
Requires-Dist: pyzmq<27,>=26.0.3
Requires-Dist: xmltodict==0.14.2
Dynamic: license-file
